ATM1b_QFIT/__init__.py
ATM1b_QFIT/count_leap_seconds.py
ATM1b_QFIT/read_ATM1b_QFIT_binary.py
ATM1b_QFIT/time.py
ATM1b_QFIT/utilities.py
ATM1b_QFIT-1.0.1.data/scripts/nsidc_convert_ILATM1b.py
test/__init__.py
test/conftest.py
test/test_leap_seconds.py
ATM1b_QFIT-1.0.1.dist-info/LICENSE
ATM1b_QFIT-1.0.1.dist-info/METADATA
ATM1b_QFIT-1.0.1.dist-info/WHEEL
ATM1b_QFIT-1.0.1.dist-info/top_level.txt
ATM1b_QFIT-1.0.1.dist-info/RECORD
