Metadata-Version: 2.1
Name: ATM1b-QFIT
Version: 1.0.1
Summary: Python-based reader for Level-1b Airborne Topographic Mapper (ATM) QFIT binary data products
Home-page: https://github.com/tsutterley/read-ATM1b-QFIT-binary
Author: Tyler Sutterley
Author-email: tsutterl@uw.edu
License: MIT
Keywords: NSIDC,Operation IceBridge,ILATM1b,ILNSA1b,surface elevation and change
Platform: UNKNOWN
Classifier: Development Status :: 3 - Alpha
Classifier: Intended Audience :: Science/Research
Classifier: Topic :: Scientific/Engineering :: Physics
Classifier: License :: OSI Approved :: MIT License
Classifier: Programming Language :: Python :: 3
Classifier: Programming Language :: Python :: 3.6
Classifier: Programming Language :: Python :: 3.7
Classifier: Programming Language :: Python :: 3.8
License-File: LICENSE
Requires-Dist: future
Requires-Dist: lxml
Requires-Dist: numpy
